formica/__init__.py
formica/main.py
formica/package-lock.json
formica/settings.py
formica/config_templates/__init__.py
formica/config_templates/default_formica.ini
formica/config_templates/logging_config.json
formica/config_templates/test.ini
formica/connection/__init__.py
formica/connection/connection.py
formica/execution/__init__.py
formica/execution/context.py
formica/execution/device_run.py
formica/execution/task.py
formica/executor/__init__.py
formica/executor/executor.py
formica/models/__init__.py
formica/models/constant.py
formica/models/models.py
formica/models/request_models.py
formica/node/__init__.py
formica/node/flow.py
formica/node/nodes.py
formica/scheduler/__init__.py
formica/scheduler/scheduler.py
formica/utils/__init__.py
formica/utils/mock_data.py
formica/utils/session.py
formica/utils/validate.py
formica/utils/workload.py
formica/utils/mock_data/mock_data.json
formica/utils/mock_data/mock_users.json
formica/web/__init__.py
formica/web/main.py
formica/web/users.py
formica/web/web_routes.py
formica/web/api_routes/__init__.py
formica/web/api_routes/credential.py
formica/web/api_routes/device.py
formica/web/api_routes/device_set.py
formica/web/api_routes/flow.py
formica/web/api_routes/flow_run.py
formica/web/api_routes/flow_version.py
formica/web/api_routes/group.py
formica/web/api_routes/main.py
formica/web/api_routes/user.py
formica/web/dist/favicon.ico
formica/web/dist/index.html
formica/web/dist/placeholder-logo.png
formica/web/dist/placeholder-logo.svg
formica/web/dist/placeholder-user.jpg
formica/web/dist/placeholder.jpg
formica/web/dist/placeholder.svg
formica/web/dist/vite.svg
formica/web/dist/assets/index-CIrOXhSR.js
formica/web/dist/assets/index-CaszdACZ.js
formica/web/dist/assets/index-D0vJxrAl.css
formica/web/dist/assets/index-DMCXBtQh.css
pyformica-0.1.9.dist-info/METADATA
pyformica-0.1.9.dist-info/WHEEL
pyformica-0.1.9.dist-info/entry_points.txt
pyformica-0.1.9.dist-info/RECORD
